LICENSE.lic
MANIFEST.in
README.rst
change.log
setup.cfg
setup.py
cryptoshop/__init__.py
cryptoshop/_cascade_engine.py
cryptoshop/_chunk_engine.py
cryptoshop/_derivation_engine.py
cryptoshop/_nonce_engine.py
cryptoshop/_settings.py
cryptoshop/cryptoshop.py
cryptoshop.egg-info/PKG-INFO
cryptoshop.egg-info/SOURCES.txt
cryptoshop.egg-info/dependency_links.txt
cryptoshop.egg-info/requires.txt
cryptoshop.egg-info/top_level.txt
doc/protocol.graphml
doc/protocol.jpg
testing/cryptoshop/encrypt.me
testing/cryptoshop/encrypt.me.cryptoshop