Metadata-Version: 1.1
Name: cryptoshop
Version: 2.0.1
Summary: Encrypt and decrypt file or string in GCM mode with AES, Serpent or Twofish as secure as possible.
Home-page: https://github.com/Antidote1911/cryptoshop
Author: Fabrice Corraire
Author-email: antidote1911@gmail.com
License: UNKNOWN
Keywords: aes,encrypt,decrypt,encryption,decryption,serpent,argon,secure,crypto,cryptography,twofish,gcm,argon2,botan
Platform: UNKNOWN
Classifier: Programming Language :: Python
Classifier: Development Status :: 5 - Production/Stable
Classifier: License :: OSI Approved :: GNU General Public License v3 (GPLv3)
Classifier: Natural Language :: English
Classifier: Operating System :: OS Independent
Classifier: Programming Language :: Python :: 3
Classifier: Topic :: Security
Classifier: Topic :: Security :: Cryptography
Classifier: Topic :: Software Development
